uas/__init__.py
uas/config/uas.py
uas/controllers/AuthController.py
uas/controllers/__init__.py
uas/databases/migrations/2023_05_10_135336_prepare_uas_table.py
uas/databases/migrations/2023_05_10_135337_create_ip_addresses_table.py
uas/databases/migrations/2023_05_10_135339_create_user_agents_table.py
uas/databases/migrations/2023_05_10_135340_create_email_tokens_table.py
uas/databases/migrations/2023_05_10_135341_create_user_tokens_table.py
uas/databases/migrations/2023_05_10_135342_create_session_users_table.py
uas/databases/migrations/2023_05_10_135343_create_user_sessions_table.py
uas/databases/migrations/2023_05_10_135344_create_access_locations_table.py
uas/databases/migrations/2023_05_10_135345_create_pending_logins_table.py
uas/databases/migrations/2023_05_10_135346_create_users_table.py
uas/databases/migrations/2023_05_10_135347_create_countries.py
uas/databases/migrations/2023_05_10_135348_create_profiles.py
uas/databases/seeds/__init__.py
uas/databases/seeds/database_seeder.py
uas/databases/seeds/user_table_seeder.py
uas/middlewares/RegisterAccessLocationMiddleware.py
uas/middlewares/RegisterAuthVisitMiddleware.py
uas/middlewares/RegisterVisitMiddleware.py
uas/middlewares/SyncSessionUserMiddleware.py
uas/middlewares/__init__.py
uas/models/AccessLocation.py
uas/models/Country.py
uas/models/EmailToken.py
uas/models/IpAddress.py
uas/models/PendingLogin.py
uas/models/Profile.py
uas/models/SessionUser.py
uas/models/User.py
uas/models/UserAgent.py
uas/models/UserSession.py
uas/models/UserToken.py
uas/providers/UASProvider.py
uas/providers/__init__.py
uas/services/AuthService.py
masonite_uas-0.0.1.dist-info/LICENSE
masonite_uas-0.0.1.dist-info/METADATA
masonite_uas-0.0.1.dist-info/WHEEL
masonite_uas-0.0.1.dist-info/top_level.txt
masonite_uas-0.0.1.dist-info/RECORD
