Metadata-Version: 2.1
Name: masonite-uas
Version: 0.0.1
Summary: A simple user account system for Masonite with email-verifications, password-resets, two-factor authentication, etc.
Home-page: https://github.com/lvjhn/masonite-servicing
Author: LJ S.A.
Author-email: lvjhn.mx@gmail.com
License: MIT license
Keywords: Masonite,Python,Development
Platform: UNKNOWN
Classifier: Development Status :: 3 - Alpha
Classifier: Intended Audience :: Developers
Classifier: Topic :: Software Development :: Build Tools
Classifier: Environment :: Web Environment
Classifier: License :: OSI Approved :: MIT License
Classifier: Operating System :: OS Independent
Classifier: Programming Language :: Python :: 3.6
Classifier: Programming Language :: Python :: 3.7
Classifier: Programming Language :: Python :: 3.8
Classifier: Programming Language :: Python :: 3.9
Classifier: Topic :: Internet :: WWW/HTTP
Classifier: Topic :: Internet :: WWW/HTTP :: Dynamic Content
Classifier: Topic :: Internet :: WWW/HTTP :: WSGI
Classifier: Topic :: Software Development :: Libraries :: Application Frameworks
Classifier: Topic :: Software Development :: Libraries :: Python Modules
Classifier: Framework :: Masonite
License-File: LICENSE
Requires-Dist: masonite (>=4.0)
Provides-Extra: dev
Requires-Dist: black ; extra == 'dev'
Requires-Dist: coverage ; extra == 'dev'
Requires-Dist: flake8 ; extra == 'dev'
Requires-Dist: pytest ; extra == 'dev'
Requires-Dist: pytest-cov ; extra == 'dev'
Requires-Dist: twine (>=1.5.0) ; extra == 'dev'
Requires-Dist: wheel ; extra == 'dev'
